setup.py
mdx_foldouts/__init__.py
mdx_foldouts.egg-info/PKG-INFO
mdx_foldouts.egg-info/SOURCES.txt
mdx_foldouts.egg-info/dependency_links.txt
mdx_foldouts.egg-info/requires.txt
mdx_foldouts.egg-info/top_level.txt