Metadata-Version: 1.1
Name: mdx-foldouts
Version: 1.0.0
Summary: Ability to model callouts in Markdown
Home-page: https://github.com/marcoceppi/mdx_foldouts
Author: Marco Ceppi
Author-email: marco@ceppi.net
License: UNKNOWN
Platform: UNKNOWN
Classifier: Environment :: Web Environment
Classifier: Intended Audience :: Developers
Classifier: Operating System :: OS Independent
Classifier: Programming Language :: Python
